{
"version":1,
"category":1,
"effectiveness":{
 "gen1": [4, 2, 1, 1, 2, 4, 1, 0, 0, 2, 2, 2, 2, 1, 4, 2, 0],
 "gen2": [4, 2, 1, 1, 2, 4, 1, 0, 4, 2, 2, 2, 2, 1, 4, 2, 4],
 "gen3": [4, 2, 1, 1, 2, 4, 1, 0, 4, 2, 2, 2, 2, 1, 4, 2, 4],
 "gen4": [4, 2, 1, 1, 2, 4, 1, 0, 4, 2, 2, 2, 2, 1, 4, 2, 4],
 "gen5": [4, 2, 1, 1, 2, 4, 1, 0, 4, 2, 2, 2, 2, 1, 4, 2, 4],
 "gen6": [4, 2, 1, 1, 2, 4, 1, 0, 4, 2, 2, 2, 2, 1, 4, 2, 4, 1],
 "inverse": [1, 2, 4, 4, 2, 1, 4, 4, 4, 1, 2, 2, 2, 4, 1, 2, 1, 4]
},
"name":{
 "English": "Fighting",
 "日本語": "かくとう",
 "Français": "Combat",
 "Deutsch": "Kampf",
 "Italiano": "Lotta",
 "한글": "격투",
 "Español": "Peleador"
}
}